spells/__init__.py
"spells/__main__,py"
spells/env/Lib/site-packages/aenum/__init__.py
spells/env/Lib/site-packages/aenum/CHANGES
spells/env/Lib/site-packages/aenum/LICENSE
spells/env/Lib/site-packages/aenum/README
spells/env/Lib/site-packages/aenum/test_v3.py
spells/env/Lib/site-packages/aenum-2.2.6.dist-info/INSTALLER
spells/env/Lib/site-packages/aenum-2.2.6.dist-info/METADATA
spells/env/Lib/site-packages/aenum-2.2.6.dist-info/RECORD
spells/env/Lib/site-packages/aenum-2.2.6.dist-info/top_level.txt
spells/env/Lib/site-packages/aenum-2.2.6.dist-info/WHEEL
spells/env/Lib/site-packages/click/__init__.py
spells/env/Lib/site-packages/click/_compat.py
spells/env/Lib/site-packages/click/_termui_impl.py
spells/env/Lib/site-packages/click/_textwrap.py
spells/env/Lib/site-packages/click/_unicodefun.py
spells/env/Lib/site-packages/click/_winconsole.py
spells/env/Lib/site-packages/click/core.py
spells/env/Lib/site-packages/click/decorators.py
spells/env/Lib/site-packages/click/exceptions.py
spells/env/Lib/site-packages/click/formatting.py
spells/env/Lib/site-packages/click/globals.py
spells/env/Lib/site-packages/click/parser.py
spells/env/Lib/site-packages/click/shell_completion.py
spells/env/Lib/site-packages/click/termui.py
spells/env/Lib/site-packages/click/testing.py
spells/env/Lib/site-packages/click/types.py
spells/env/Lib/site-packages/click/utils.py
spells/env/Lib/site-packages/click-8.0.0a1.dist-info/INSTALLER
spells/env/Lib/site-packages/click-8.0.0a1.dist-info/LICENSE.rst
spells/env/Lib/site-packages/click-8.0.0a1.dist-info/METADATA
spells/env/Lib/site-packages/click-8.0.0a1.dist-info/RECORD
spells/env/Lib/site-packages/click-8.0.0a1.dist-info/top_level.txt
spells/env/Lib/site-packages/click-8.0.0a1.dist-info/WHEEL
spells/env/Lib/site-packages/cutesnowflakes/__init__.py
spells/env/Lib/site-packages/cutesnowflakes/cutesnowflakes.py
spells/env/Lib/site-packages/cutesnowflakes-1.0.1.dist-info/INSTALLER
spells/env/Lib/site-packages/cutesnowflakes-1.0.1.dist-info/METADATA
spells/env/Lib/site-packages/cutesnowflakes-1.0.1.dist-info/RECORD
spells/env/Lib/site-packages/cutesnowflakes-1.0.1.dist-info/REQUESTED
spells/env/Lib/site-packages/cutesnowflakes-1.0.1.dist-info/top_level.txt
spells/env/Lib/site-packages/cutesnowflakes-1.0.1.dist-info/WHEEL
spells/env/Lib/site-packages/easy_install.py
spells/env/Lib/site-packages/numpy/.libs/libopenblas.QVLO2T66WEPI7JZ63PS3HMOHFEY472BC.gfortran-win_amd64.dll
spells/env/Lib/site-packages/numpy/__config__.py
spells/env/Lib/site-packages/numpy/__init__.cython-30.pxd
spells/env/Lib/site-packages/numpy/__init__.pxd
spells/env/Lib/site-packages/numpy/__init__.py
spells/env/Lib/site-packages/numpy/_distributor_init.py
spells/env/Lib/site-packages/numpy/_globals.py
spells/env/Lib/site-packages/numpy/_pytesttester.py
spells/env/Lib/site-packages/numpy/compat/__init__.py
spells/env/Lib/site-packages/numpy/compat/_inspect.py
spells/env/Lib/site-packages/numpy/compat/py3k.py
spells/env/Lib/site-packages/numpy/compat/setup.py
spells/env/Lib/site-packages/numpy/compat/tests/__init__.py
spells/env/Lib/site-packages/numpy-1.19.3.dist-info/entry_points.txt
spells/env/Lib/site-packages/numpy-1.19.3.dist-info/INSTALLER
spells/env/Lib/site-packages/numpy-1.19.3.dist-info/LICENSE.txt
spells/env/Lib/site-packages/numpy-1.19.3.dist-info/LICENSES_bundled.txt
spells/env/Lib/site-packages/numpy-1.19.3.dist-info/METADATA
spells/env/Lib/site-packages/numpy-1.19.3.dist-info/RECORD
spells/env/Lib/site-packages/numpy-1.19.3.dist-info/top_level.txt
spells/env/Lib/site-packages/numpy-1.19.3.dist-info/WHEEL
spells/env/Lib/site-packages/Pillow-8.0.0.dist-info/INSTALLER
spells/env/Lib/site-packages/Pillow-8.0.0.dist-info/LICENSE
spells/env/Lib/site-packages/Pillow-8.0.0.dist-info/METADATA
spells/env/Lib/site-packages/Pillow-8.0.0.dist-info/RECORD
spells/env/Lib/site-packages/Pillow-8.0.0.dist-info/top_level.txt
spells/env/Lib/site-packages/Pillow-8.0.0.dist-info/WHEEL
spells/env/Lib/site-packages/Pillow-8.0.0.dist-info/zip-safe
spells/env/Lib/site-packages/pip-20.2.3.dist-info/entry_points.txt
spells/env/Lib/site-packages/pip-20.2.3.dist-info/INSTALLER
spells/env/Lib/site-packages/pip-20.2.3.dist-info/LICENSE.txt
spells/env/Lib/site-packages/pip-20.2.3.dist-info/METADATA
spells/env/Lib/site-packages/pip-20.2.3.dist-info/RECORD
spells/env/Lib/site-packages/pip-20.2.3.dist-info/REQUESTED
spells/env/Lib/site-packages/pip-20.2.3.dist-info/top_level.txt
spells/env/Lib/site-packages/pip-20.2.3.dist-info/WHEEL
spells/env/Lib/site-packages/setuptools-49.2.1.dist-info/dependency_links.txt
spells/env/Lib/site-packages/setuptools-49.2.1.dist-info/entry_points.txt
spells/env/Lib/site-packages/setuptools-49.2.1.dist-info/INSTALLER
spells/env/Lib/site-packages/setuptools-49.2.1.dist-info/LICENSE
spells/env/Lib/site-packages/setuptools-49.2.1.dist-info/METADATA
spells/env/Lib/site-packages/setuptools-49.2.1.dist-info/RECORD
spells/env/Lib/site-packages/setuptools-49.2.1.dist-info/REQUESTED
spells/env/Lib/site-packages/setuptools-49.2.1.dist-info/top_level.txt
spells/env/Lib/site-packages/setuptools-49.2.1.dist-info/WHEEL
spells/env/Lib/site-packages/setuptools-49.2.1.dist-info/zip-safe
spells-0.0.5.dist-info/LICENSE
spells-0.0.5.dist-info/WHEEL
spells-0.0.5.dist-info/METADATA
spells-0.0.5.dist-info/RECORD
