Metadata-Version: 2.1
Name: spells
Version: 0.0.5
Summary: Developer-friendly cross-platform build scripts and project automation.
License: MIT
Author: CodeBizarre
Requires-Python: >=3.7
Classifier: License :: OSI Approved :: MIT License
Classifier: Programming Language :: Python :: 3
Classifier: Programming Language :: Python :: 3.7
Classifier: Programming Language :: Python :: 3.8
Classifier: Programming Language :: Python :: 3.9
